whoswho/__init__.py
whoswho/model.py
whoswho/utils.py
whoswho/who.py
whoswho/config/__init__.py
whoswho/config/settings.py
whoswho/config/suffixes.py
whoswho/config/titles.py
whoswho-0.2.1.dist-info/LICENSE
whoswho-0.2.1.dist-info/METADATA
whoswho-0.2.1.dist-info/WHEEL
whoswho-0.2.1.dist-info/top_level.txt
whoswho-0.2.1.dist-info/RECORD
