Metadata-Version: 2.1
Name: whoswho
Version: 0.2.1
Summary: A simple python library for determining whether two names describe the same person.
Home-page: https://www.github.com/rliebz/whoswho
Author: Robert Liebowitz
Author-email: rliebz@gmail.com
License: UNKNOWN
Keywords: whoswho,name,match,parser
Platform: UNKNOWN
Classifier: Intended Audience :: Developers
Classifier: License :: OSI Approved :: MIT License
Classifier: Natural Language :: English
Classifier: Programming Language :: Python
Classifier: Programming Language :: Python :: 2.6
Classifier: Programming Language :: Python :: 2.7
Classifier: Programming Language :: Python :: 3.3
Classifier: Programming Language :: Python :: 3.4
Classifier: Topic :: Software Development :: Libraries :: Python Modules
Classifier: Topic :: Text Processing :: Linguistic
Requires-Dist: nameparser
